{
    "type": "meadow:cooking",
    "result": {
        "item": "crabbersdelight:bisque"
    },
    "ingredients": [
        {
            "item": "minecraft:bowl"
        },
        [
            {
                "tag": "crabbersdelight:cooked_seafood"
            },
            {
                "tag": "crabbersdelight:raw_seafood"
            }
        ],
        {
            "item": "farmersdelight:onion"
        },
        {
            "item": "farmersdelight:rice"
        },
        {
            "item": "minecraft:carrot"
        },
        {
            "tag": "forge:milk"
        }
    ],
    "conditions": [
        {
            "type": "forge:mod_loaded",
            "modid": "crabbersdelight"
        },
        {
            "type": "forge:mod_loaded",
            "modid": "meadow"
        }
    ]
}