{
    "type": "candlelight:pot_cooking",
    "result": {
        "item": "farmersdelight:pumpkin_soup"
    },
    "ingredients": [
        {
            "item": "farmersdelight:pumpkin_slice"
        },
        {
            "tag": "c:salad_ingredients"
        },
        {
            "tag": "c:raw_pork"
        },
        {
            "tag": "c:milk"
        }
    ],
    "fabric:load_conditions": [
        {
            "condition": "fabric:all_mods_loaded",
            "values": [
                "farmersdelight",
                "candlelight"
            ]
        }
    ],
    "conditions": [
        {
            "type": "forge:mod_loaded",
            "modid": "farmersdelight"
        },
        {
            "type": "forge:mod_loaded",
            "modid": "candlelight"
        }
    ]
}