{
    "type": "farmersdelight:pot_cooking",
    "result": {
        "item": "brewinandchewin:vegetable_omelet"
    },
    "ingredients": [
        {
            "item": "brewinandchewin:flaxen_cheese_wedge"
        },
        {
            "tag": "c:eggs"
        },
        {
            "tag": "c:eggs"
        },
        {
            "item": "farmersdelight:onion"
        },
        {
            "tag": "c:crops/carrot"
        }
    ],
    "container": {
        "item": "minecraft:air"
    },
    "fabric:load_conditions": [
        {
            "condition": "fabric:all_mods_loaded",
            "values": [
                "brewinandchewin",
                "farmersdelight"
            ]
        }
    ]
}