{
    "type": "farmersdelight:cutting",
    "ingredients": [
        {
            "item": "meadow:buffalo_cheese_block"
        }
    ],
    "result": [
        {
            "item": "meadow:piece_of_buffalo_cheese",
            "count": 4
        }
    ],
    "tool": {
        "tag": "forge:tools/knives"
    },
    "conditions": [
        {
            "type": "forge:mod_loaded",
            "modid": "meadow"
        },
        {
            "type": "forge:mod_loaded",
            "modid": "farmersdelight"
        }
    ]
}