{
    "type": "bakery:pot_cooking",
    "result": {
        "item": "frightsdelight:punch_soul_berry",
        "count": 4
    },
    "ingredients": [
        {
            "item": "frightsdelight:soul_berry"
        },
        {
            "item": "frightsdelight:soul_berry"
        },
        {
            "item": "minecraft:sugar"
        },
        {
            "item": "minecraft:water_bucket"
        }
    ],
    "container": {
        "item": "minecraft:glass_bottle",
        "count": 4
    }
}