{
    "type": "meadow:cooking",
    "result": {
        "item": "expandeddelight:peanut_honey_soup"
    },
    "ingredients": [
        {
            "tag": "c:milk"
        },
        {
            "tag": "c:crops/peanut"
        },
        {
            "tag": "c:crops/peanut"
        },
        {
            "item": "minecraft:honey_bottle"
        },
        {
            "item": "minecraft:bowl"
        }
    ],
    "container": null,
    "fabric:load_conditions": [
        {
            "condition": "fabric:all_mods_loaded",
            "values": [
                "expandeddelight",
                "meadow"
            ]
        }
    ]
}