{
    "type": "bakery:pot_cooking",
    "result": {
        "item": "vintagedelight:pepper_jam_mason_jar"
    },
    "ingredients": [
        {
            "item": "vintagedelight:pickled_pepper"
        },
        {
            "item": "vintagedelight:pickled_pepper"
        },
        {
            "item": "vintagedelight:pickled_pepper"
        },
        {
            "item": "vintagedelight:pickled_pepper"
        },
        {
            "item": "vintagedelight:pickled_pepper"
        },
        {
            "item": "minecraft:sugar"
        }
    ],
    "container": {
        "item": "vintagedelight:mason_jar"
    }
}